{"schema":{"sessionID":"A9946036-DA18-4738-9BA9-13266827A247","noiseNodeIDs":["EY_418","AM_438","BK_964","AV_967","LG_387","HG_747","WK_670","BY_835"],"nodePrefixMap":{"F":"彩_","D":"匴_","X":"式_","N":"縞_","V":"礫_","T":"礎_","S":"錠_"},"tagOpen":"_TOKEN_","createdAt":799142451.508777,"schemaVersion":1777449651,"nodeOpen":"__ast_","opNameMap":{"OP.VAR":"BM_SHELL_L30","OP.TYPE":"ΔΘ_VECTOR_B67","OP.PROC":"ΩΛ_QUEUE_M39","OP.FUNC":"ΨΦ_BLOCK_X83","OP.SECRET":"YR_QUEUE_H12","OP.FLOW":"KZ_STACK_H98","OP.STORE":"QX_TENSOR_L34","OP.NET":"VΩ_QUEUE_L98"},"secretClose":"_","nodeClose":"__","tagClose":"_","secretOpen":"_VERANTYX_","noiseLevel":2,"kanjiCategoryMap":{"flow":"湧","secret":"錠","variable":"礫","type":"礎","network":"縞","process":"式","function":"彩","storage":"匴"}},"reverseMap":{"礫_8":"generated","礫_4":"module122","礎_3":"Auto","礎_2":"Init","礎_1":"Module","礫_7":"module","礫_1":"export","礫_2":"name","礫_3":"const","礫_5":"log","礫_6":"console"},"nodeMap":{"const":"礫_3","name":"礫_2","module122":"礫_4","Auto":"礎_3","generated":"礫_8","Module":"礎_1","export":"礫_1","log":"礫_5","module":"礫_7","console":"礫_6","Init":"礎_2"}}