{"nodeMap":{"Init":"礎_3","console":"霾_5","Auto":"礎_1","const":"霾_4","generated":"霾_8","export":"霾_1","Module":"礎_2","module":"霾_2","name":"霾_3","module36":"霾_7","log":"霾_6"},"schema":{"createdAt":799142456.675825,"secretOpen":"_ASTNODE_","tagOpen":"__node_","nodeClose":"_","kanjiCategoryMap":{"variable":"霾","process":"式","flow":"流","storage":"匼","type":"礎","secret":"蔽","network":"紋","function":"覇"},"noiseNodeIDs":["KD_808","DF_982","ZK_789","LG_723","GD_538","VG_522","VL_585","ZG_242"],"opNameMap":{"OP.TYPE":"RΓ_SHELL_A15","OP.NET":"KZ_HEAP_Y96","OP.FUNC":"QX_NODE_C30","OP.FLOW":"ΓΞ_HEAP_K47","OP.SECRET":"UΦ_STACK_L33","OP.VAR":"VΩ_GRAPH_F97","OP.STORE":"ZK_STREAM_X94","OP.PROC":"UΦ_STACK_D25"},"nodePrefixMap":{"N":"紋_","X":"式_","V":"霾_","S":"蔽_","T":"礎_","F":"覇_","D":"匼_"},"nodeOpen":"_OPAQUE_","tagClose":"__","schemaVersion":1777449656,"noiseLevel":2,"secretClose":"_","sessionID":"EC644946-F420-47B3-9658-1E3A1014FE9F"},"reverseMap":{"霾_5":"console","礎_1":"Auto","霾_7":"module36","礎_3":"Init","礎_2":"Module","霾_2":"module","霾_3":"name","霾_1":"export","霾_4":"const","霾_8":"generated","霾_6":"log"}}