{"schema":{"kanjiCategoryMap":{"flow":"湧","secret":"蔽","variable":"霞","type":"廨","network":"緞","process":"技","function":"傑","storage":"医"},"secretOpen":"_TOKEN_","tagOpen":"__node_","createdAt":799142539.580032,"nodeClose":"__","noiseNodeIDs":["ZG_481","XK_976","MF_884","MD_996","HB_594","FV_224","WL_766","DK_547"],"opNameMap":{"OP.VAR":"ΔΘ_TREE_B78","OP.TYPE":"ΨΦ_TREE_E74","OP.SECRET":"WΔ_HEAP_X93","OP.FLOW":"ΨΦ_STACK_H62","OP.STORE":"WΔ_GRAPH_Y53","OP.FUNC":"ΩΛ_TREE_Y3","OP.NET":"ΩΛ_STACK_Y40","OP.PROC":"ΨΦ_NODE_K79"},"nodePrefixMap":{"S":"蔽_","T":"廨_","X":"技_","F":"傑_","N":"緞_","D":"医_","V":"霞_"},"nodeOpen":"__jcross_","tagClose":"__","schemaVersion":1777449739,"noiseLevel":2,"secretClose":"_","sessionID":"730157FB-4688-4455-ACF1-642A1805D2B2"},"nodeMap":{"module121":"霞_2","export":"霞_7","Module":"廨_2","generated":"霞_1","name":"霞_3","log":"霞_5","Auto":"廨_1","const":"霞_6","console":"霞_4","Init":"廨_3","module":"霞_8"},"reverseMap":{"霞_1":"generated","霞_3":"name","霞_8":"module","霞_6":"const","霞_4":"console","霞_2":"module121","霞_5":"log","廨_2":"Module","廨_1":"Auto","霞_7":"export","廨_3":"Init"}}